AUTHORS
CHANGELOG.rst
LICENSE
MANIFEST.in
README.rst
setup.py
dreipol_django_fagungis.egg-info/PKG-INFO
dreipol_django_fagungis.egg-info/SOURCES.txt
dreipol_django_fagungis.egg-info/dependency_links.txt
dreipol_django_fagungis.egg-info/namespace_packages.txt
dreipol_django_fagungis.egg-info/not-zip-safe
dreipol_django_fagungis.egg-info/requires.txt
dreipol_django_fagungis.egg-info/top_level.txt
fagungis/__init__.py
fagungis/example_fabfile.py
fagungis/tasks.py
fagungis/conf/nginx.conf
fagungis/conf/nginx_https.conf
fagungis/conf/supervisord.conf
fagungis/scripts/rungunicorn.sh