Metadata-Version: 1.1
Name: dreipol-django-fagungis
Version: 0.0.21
Summary: DJANGO + FAbric + GUnicorn + NGInx + Supervisor deployment for dreipol
Home-page: https://github.com/dreipol/django-fagungis
Author: Denis Darii
Author-email: denis.darii@gmail.com
License: BSD License
Download-URL: https://github.com/dreipol/django-fagungis
Keywords: django fabric gunicorn nginx supervisor
Platform: UNKNOWN
Classifier: Development Status :: 3 - Alpha
Classifier: Environment :: Console
Classifier: Framework :: Django
Classifier: Intended Audience :: Developers
Classifier: Intended Audience :: System Administrators
Classifier: Operating System :: MacOS :: MacOS X
Classifier: Operating System :: Unix
Classifier: Operating System :: POSIX
Classifier: Programming Language :: Python
Classifier: Programming Language :: Python :: 2.5
Classifier: Programming Language :: Python :: 2.6
Classifier: Programming Language :: Python :: 2.7
Classifier: Topic :: Software Development
Classifier: Topic :: Software Development :: Build Tools
Classifier: Topic :: Software Development :: Libraries
Classifier: Topic :: Software Development :: Libraries :: Python Modules
Classifier: Topic :: System :: Clustering
Classifier: Topic :: System :: Software Distribution
Classifier: Topic :: System :: Systems Administration
